{
  "menu": [
    {
      "url": "/",
      "name": "Dashboard",
      "i18n": "Dashboard",
      "slug": "dashboard",
      "icon": "settings_input_svideo",
      "tagcustom": "badge pill orange float-right mr-10"
    },    
    {
      "navheader": "ADMINISTRATIVO",
      "icon": "more_horiz"
    },
    {
      "url": "javascript:void(0)",
      "name": "Requisitos",
      "i18n": "Requisitos",
      "class": "collapsible-header waves-effect waves-cyan",
      "slug": "requisitos",
      "icon": "content_paste",
      "tagcustom": "badge pill orange float-right mr-10",
      "submenu": [
        {
          "url": "req1",
          "name": "Req1",
          "i18n": "Req1",
          "slug": "req1"
        },
        {
          "url": "req2",
          "name": "Req2",
          "i18n": "Req2",
          "slug": "req2"
        },
        {
          "url": "req3",
          "name": "Req3",
          "i18n": "Req3",
          "slug": "req3"
        },
        {
          "url": "req4",
          "name": "Req4",
          "i18n": "Req4",
          "slug": "req4"
        }
      ]
    },
    {
      "url": "javascript:void(0)",
      "name": "Propostas",
      "i18n": "Propostas",
      "class": "collapsible-header waves-effect waves-cyan",
      "slug": "propostas",
      "icon": "receipt",
      "tagcustom": "badge pill orange float-right mr-10",
      "submenu": [
        {
          "url": "virtual",
          "name": "Servidorvirtual",
          "i18n": "virtual",
          "slug": "virtual"
        },
        {
          "url": "armazenamento",
          "name": "Armazenamento",
          "i18n": "Armazenamento",
          "slug": "armazenamento"
        },
        {
          "url": "hospedagem",
          "name": "Hospedagem",
          "i18n": "Hospedagem",
          "slug": "hospedagem"
        },
        {
          "url": "desenvolvimento",
          "name": "Desenvolvimento",
          "i18n": "Desenvolvimento",
          "slug": "desenvolvimento"
        },
        {
          "url": "consultoria",
          "name": "Consultoria",
          "i18n": "Consultoria",
          "slug": "consultoria"
        }
      ]
    },
    {
      "url": "javascript:void(0)",
      "name": "Testes",
      "i18n": "Testes",
      "class": "collapsible-header waves-effect waves-cyan",
      "slug": "testes",
      "icon": "assignment_turned_in",
      "tagcustom": "badge pill orange float-right mr-10",
      "submenu": [
        {
          "url": "testes1",
          "name": "Testes1",
          "i18n": "Testes1",
          "slug": "testes1"
        },
        {
          "url": "testes2",
          "name": "Testes2",
          "i18n": "Testes2",
          "slug": "testes2"
        },
        {
          "url": "testes3",
          "name": "Testes3",
          "i18n": "Testes3",
          "slug": "testes3"
        },
        {
          "url": "testes4",
          "name": "Testes4",
          "i18n": "Testes4",
          "slug": "testes4"
        }
      ]
    },
    {
      "url": "usuarios",
      "name": "Usuarios",
      "i18n": "Usuarios",
      "slug": "usuarios",
      "icon": "person_outline",
      "tagcustom": "badge pill orange float-right mr-10"
    },
    {
      "navheader": "AUDITORIA",
      "icon": "more_horiz"
    },
    {
      "url": "historico",
      "name": "Historico",
      "i18n": "Historico",
      "slug": "historico",
      "icon": "history",
      "tagcustom": "badge pill orange float-right mr-10"
    }
  ]
}